tox_ipdb.py
tox_ipdb_plugin-1.0.dist-info/LICENSE
tox_ipdb_plugin-1.0.dist-info/METADATA
tox_ipdb_plugin-1.0.dist-info/WHEEL
tox_ipdb_plugin-1.0.dist-info/entry_points.txt
tox_ipdb_plugin-1.0.dist-info/top_level.txt
tox_ipdb_plugin-1.0.dist-info/RECORD
