Metadata-Version: 2.1
Name: tox-ipdb-plugin
Version: 1.0
Summary: Tox plugin which installs ipdb in tox environments.
Home-page: https://github.com/CZ-NIC/tox-ipdb-plugin
Author: Vlastimil Zíma
Author-email: vlastimil.zima@nic.cz
License: GPLv3+
Classifier: Development Status :: 2 - Pre-Alpha
Classifier: Environment :: Plugins
Classifier: Framework :: tox
Classifier: Intended Audience :: Developers
Classifier: License :: OSI Approved :: GNU General Public License v3 or later (GPLv3+)
Classifier: Operating System :: OS Independent
Classifier: Programming Language :: Python
Classifier: Programming Language :: Python :: 3.8
Classifier: Programming Language :: Python :: 3.9
Classifier: Programming Language :: Python :: 3.10
Classifier: Programming Language :: Python :: 3.11
Classifier: Programming Language :: Python :: 3.12
Classifier: Topic :: Software Development
Classifier: Topic :: Software Development :: Debuggers
Classifier: Topic :: Software Development :: Testing
Requires-Python: ~=3.8
License-File: LICENSE
Requires-Dist: tox >=3.0
Provides-Extra: quality
Requires-Dist: doc8 ; extra == 'quality'
Requires-Dist: mypy ; extra == 'quality'
Requires-Dist: ruff ; extra == 'quality'
